big_fiubrother_classification/__init__.py
big_fiubrother_classification/classifier_support_vector.py
big_fiubrother_classification/face_embedder_factory.py
big_fiubrother_classification/face_embedder_mvds_facenet.py
big_fiubrother_classification/face_embedder_tensorflow_facenet.py
big_fiubrother_classification/config/config_mvds_facenet.yaml
big_fiubrother_classification/config/config_tensorflow_facenet.yaml
big_fiubrother_classification/model/convert_facenet.py
big_fiubrother_classification/model/inception_resnet_v1.py
big_fiubrother_classification/model/prepare_models.sh
big_fiubrother_classification-0.1.7.data/scripts/big_fiubrother_classification_demo_classifier.py
big_fiubrother_classification-0.1.7.data/scripts/big_fiubrother_classification_demo_embedding.py
big_fiubrother_classification-0.1.7.data/scripts/big_fiubrother_classification_install.py
big_fiubrother_classification-0.1.7.dist-info/LICENSE
big_fiubrother_classification-0.1.7.dist-info/METADATA
big_fiubrother_classification-0.1.7.dist-info/WHEEL
big_fiubrother_classification-0.1.7.dist-info/top_level.txt
big_fiubrother_classification-0.1.7.dist-info/RECORD
